README.md
setup.py
uce/__init__.py
uce.egg-info/PKG-INFO
uce.egg-info/SOURCES.txt
uce.egg-info/dependency_links.txt
uce.egg-info/top_level.txt