Metadata-Version: 2.1
Name: uce
Version: 0.0.1
Summary: µce
Home-page: https://github.com/lmrck/dnb
Author: Bülent Aldemir
Author-email: buelent@e-evolution.de
License: UNKNOWN
Platform: UNKNOWN
Classifier: Development Status :: 1 - Planning
Classifier: Programming Language :: Python :: 3
Classifier: License :: OSI Approved :: MIT License
Classifier: Operating System :: OS Independent
Requires-Python: >=3.7
